ajum/__init__.py
ajum/ajum.py
ajum/cli.py
ajum/utils.py
ajum/data/index.json
ajum-0.8.0.dist-info/LICENSE
ajum-0.8.0.dist-info/METADATA
ajum-0.8.0.dist-info/WHEEL
ajum-0.8.0.dist-info/entry_points.txt
ajum-0.8.0.dist-info/top_level.txt
ajum-0.8.0.dist-info/RECORD
