Metadata-Version: 2.1
Name: ajum
Version: 0.8.0
Summary: Tools for interacting with the "AJuM" database
Home-page: https://codeberg.org/fundevogel/we-love-ajum
Author: Martin Folkers
Author-email: hello@twobrain.io
Maintainer: Fundevogel
Maintainer-email: maschinenraum@fundevogel.de
License: MIT
Project-URL: Issues, https://codeberg.org/fundevogel/we-love-ajum/issues
Platform: UNKNOWN
Classifier: Programming Language :: Python :: 3
Classifier: License :: OSI Approved :: MIT License
Classifier: Operating System :: OS Independent
Requires-Python: >=3.6
License-File: LICENSE
Requires-Dist: aiofiles
Requires-Dist: aiohttp
Requires-Dist: bs4
Requires-Dist: click
Requires-Dist: isbnlib
Requires-Dist: lxml
Requires-Dist: pytest
Requires-Dist: requests
